kbcstorage/__init__.py
kbcstorage/base.py
kbcstorage/branches.py
kbcstorage/buckets.py
kbcstorage/client.py
kbcstorage/components.py
kbcstorage/configurations.py
kbcstorage/configurations_metadata.py
kbcstorage/files.py
kbcstorage/jobs.py
kbcstorage/retry_requests.py
kbcstorage/tables.py
kbcstorage/tables_metadata.py
kbcstorage/tokens.py
kbcstorage/triggers.py
kbcstorage/workspaces.py
kbcstorage-0.9.4.dist-info/licenses/LICENSE
kbcstorage-0.9.4.dist-info/METADATA
kbcstorage-0.9.4.dist-info/WHEEL
kbcstorage-0.9.4.dist-info/top_level.txt
kbcstorage-0.9.4.dist-info/RECORD
