Metadata-Version: 2.4
Name: kbcstorage
Version: 0.9.4
Summary: Client for Keboola Storage API
Author-email: Keboola <developers@keboola.com>
License: MIT License
Keywords: keboola,storage
Classifier: Programming Language :: Python :: 3
Classifier: License :: OSI Approved :: MIT License
Classifier: Operating System :: OS Independent
Classifier: Development Status :: 5 - Production/Stable
Requires-Python: >=3.7
License-File: LICENSE
Requires-Dist: boto3
Requires-Dist: azure-storage-blob
Requires-Dist: urllib3<2.0.0
Requires-Dist: requests
Requires-Dist: responses
Requires-Dist: python-dotenv
Requires-Dist: google-cloud-storage==3.5.0
Requires-Dist: google-auth==2.43.0
Dynamic: license-file
